[
  {
    "message": "セックスを終えた余韻の中……"
  },
  {
    "message": "裸のまま尚人と気のない雑談を交わしていた所、珍しくお母さんが部屋にやってきた。"
  },
  {
    "message": "ワザワザこのタイミングで来るという事は……つまりはそういう事。"
  },
  {
    "message": "お母さんはさっと服を脱ぐと３人寝るには狭いベッドに横たわり……私の愛液がこびり付いた尚人のペニスを、自分の女性器へと誘い込ませていく……"
  },
  {
    "name": "藤子",
    "message": "「んあっ、あっ、あふぅ……んあ、あっ、あふ……はあっ、あっ、あくっ、あふぅ……」"
  },
  {
    "message": "母と娘が同じベッドの上で横たわり、同じ男と続けてセックスをする……"
  },
  {
    "message": "一般家庭なら大問題の状況だが、私にとっては、特に異常な事ではない。"
  },
  {
    "name": "藤子",
    "message": "「……ん、んあっ、あっ、あふ……いい、いいわぁ……はっ、あっ、あくぅ……尚人さん……素敵……素敵だわぁ……」"
  },
  {
    "message": "物心ついた時には、こうして尚人とお母さんがしてる姿を自然と隣で見ていた。"
  },
  {
    "message": "初めて尚人とＨした時も、隣にお母さんが居いて３人でした。"
  },
  {
    "message": "その上、尚人の手伝いでこの寮の女生徒を仕込む為、週に２～３回は必然的に複数プレイになってしまう。"
  },
  {
    "message": "そんな私にとって、３Ｐとはよくある普通の風景……しかもそれが母だろうと、名前も知らぬ女生徒だろうがなんら変わりはないのだ。"
  },
  {
    "name": "藤子",
    "message": "「あっ、あぁん……は、はあっ！　あっ、あくっ……んあっ、はっ、はあっ！　はふっ、はぁん！」"
  },
  {
    "name": "撫子",
    "message": "（……お母さん凄い顔してる……感じてる時は私もこんな顔してるのかな……）"
  },
  {
    "message": "客を喜ばせ行為を円滑にするため気持ちよさそうにしろと尚人は仕込んでいる女生徒によく言っているが……確かにマグロより、この方がわかりやすいと思う。"
  },
  {
    "name": "撫子",
    "message": "（まぁ、私には関係ないけど……尚人としているのは別に仕事ってわけじゃないし……）"
  },
  {
    "message": "それに何より……私は自分のこんなだらしのない顔を、尚人に見られたくない。"
  },
  {
    "name": "藤子",
    "message": "「っはあっ！　あっ、はあっ！　んあっ！　はあっ、あくっ！　……んふうぅ……」"
  },
  {
    "message": "息の合った二人……流石は私が産まれるぐらいから、やりつづけている事はある。"
  },
  {
    "message": "私の母、藤木藤子は……その全てを尚人の父に買われた女。"
  },
  {
    "message": "その詳しい経緯までは聞いた事はないが……借金のカタとして二束三文で引き取ったという話を尚人から聞いた覚えがある。"
  },
  {
    "message": "そうして買い取られた後に産まれたのが私、撫子。"
  },
  {
    "message": "自分が借金のカタとして尚人の父に買われたように……私は物心がつく前から、尚人専属の性奴隷として母に売られたのだ。"
  },
  {
    "message": "その事実を突き付けられたとき……流石に小さな私の心は、それなりに傷ついてしまった。"
  },
  {
    "message": "だが尚人の奴隷が嫌なら、金を返すか沢山の男達に何十年も汚され続けると言われたら……選択肢は一つしかない。"
  },
  {
    "message": "人の人生は平等ではない……際立った才能でもない限り、誰しも生を受けた瞬間から大まかに未来は決まっている。"
  },
  {
    "message": "若い身空でそう悟った私は、流されるように尚人を受け入れる事となった。"
  },
  {
    "message": "その結果、この学園に来るまでは軽い軟禁状態で日々を過ごす事となったのだが……そもそも私はインドアな性格。"
  },
  {
    "message": "奴隷とはいえ比較的自由にお金を使う事を許されていたので、私が漫画やアニメなどの架空の世界に没頭する事になったのは必然だったのだろう。"
  },
  {
    "message": "他の人より選べる未来が極端に少ないだけ……不自由だが一生お金に困らないという点は、ある種勝ち組と言ってもいい。"
  },
  {
    "message": "周囲に蔑む目で見られる事も、家畜のようにただ日々を無駄に過ごす事も……本人にプライドさえなければ、別に苦痛にはならない。"
  },
  {
    "message": "実際の所……私はまるで可能性のない一生を過ごす事に、取り立てて不満はなかったのだ。"
  },
  {
    "message": "…………華穂さまと出会うまでは。"
  },
  {
    "message": "あの人に出会って、私は変わってしまった……"
  },
  {
    "message": "何も望まず、尚人の傍という暗い井戸の底で一生を終えるつもりだった私は、外の世界で生きる太陽のような華穂さまに魅了されてしまったのだ。"
  },
  {
    "message": "まるで物語の住人であるかのような圧倒的なまでのビジュアル……眩いまでの心の清さ。"
  },
  {
    "message": "ただ傍に居るだけで気分が高揚し、今までやる気の起きなかった事に思わずチャレンジしてみたくなる人を幸せにする陽のエネルギー。"
  },
  {
    "message": "大げさに言っているつもりはない……多分他の人から見れば、華穂さまが私にもたらした事は、然程凄い事ではなかったのだろう。"
  },
  {
    "message": "けど、私にとっては……それがとても刺激的だった。"
  },
  {
    "message": "なにせ“普通の日常”というヤツが、私からすれば非日常……まさに漫画やアニメの中だけの出来事だったのだから。"
  },
  {
    "message": "華穂さまとの日々は……暗闇の中に引きこもっていた私に……色々な可能性を……明るい未来を感じさせてくれた。"
  },
  {
    "message": "もしかしたら……今いる井戸の底から出て、自分は外にいる華穂さまの横に行けるのではと思わせてくれた。"
  },
  {
    "message": "明るい未来は……人の心にエネルギーを与えてくれる。"
  },
  {
    "message": "私は産まれて初めて……自分の意思で何かをしたいと思う力を……手に入れる事に成功したのだ。"
  },
  {
    "message": "けれど……この学園に売られた子達は、借金さえ返しきれば晴れて自由の身となるのだが……私にはそれがない。"
  },
  {
    "message": "一生、尚人の性奴隷を続けないといけないのだ。"
  },
  {
    "message": "この現状は……何か奇跡でも起きないかぎり打破する事は出来ないだろう。"
  },
  {
    "message": "だけど人は身体と心の二つで構成されている……"
  },
  {
    "message": "この身体は尚人の所有物であっても、心まで差し出した覚えはない。"
  },
  {
    "message": "せめてこの心だけでも……華穂さまの隣に居ても恥ずかしくない人間になりたい。"
  },
  {
    "message": "……いつしか私は……そう思うようになり……"
  },
  {
    "message": "その思いを成就させる方法を……自分なりに考えるようになっていたのだった……"
  },
  {
    "name": "藤子",
    "message": "「はっ、はあっ！　あっ、あくっ……ふっ、ふくぅ！　はっ、はあっ！　はあっ！　あ、あくっ！　はあっ！　あぁん！」"
  },
  {
    "name": "藤子",
    "message": "「あっ、んぐぅ！！　……な、尚人さんの太く逞しいペニスが……はっ、はあっ！　あくぅ……私の奥深くに……入ってくる……」"
  },
  {
    "name": "藤子",
    "message": "「……激しく、中をえぐられて……はあっ！　あっ、んぐぅ……子宮を突き上げられるこの感じ……はあっ！　あっ、あぁん……苦しいぐらい刺激的だわ……」"
  },
  {
    "name": "藤子",
    "message": "「……ああぁ……尚人さんの熱いペニスで……はあっ！　あっ、んんっ……私の女の大切な場所が……子宮が……気持ちよく溶けてしまいそうよ……」"
  },
  {
    "name": "藤子",
    "message": "「……はっ、ああっ！　く、くるっ！　くるわっ！　熱いのくるっ！　きたっ！　いくっ！　……尚人さん……私もう、もうイクっ！　イクわっ！」"
  },
  {
    "name": "尚人",
    "message": "「こっちももうすぐ出る……いくぞ、藤子」"
  },
  {
    "name": "藤子",
    "message": "「来てっ！　来てえぇ！　……はあっ！　はっ、あんっ！　あっ、あぐぅ……尚人さん……中に、中に出してぇ……」"
  },
  {
    "name": "藤子",
    "message": "「撫子見てて……はっ、はあっ！　……わ、私が……私が尚人さんに……思いっきり種付けされる所を……」"
  },
  {
    "name": "撫子",
    "message": "「……ちゃんと見てる……いいからさっさとイッて……」"
  },
  {
    "name": "藤子",
    "message": "「え、ええぇ……はっ、はあっ！　あっ、んあっ！　あっ、あぁん！」"
  },
  {
    "name": "藤子",
    "message": "「……んぐ、んんっ！　んはっ！　はあっ！　……あ、熱い……腰の奥熱い……はあっ！　はっ、あぁん！　熱いの……熱いの弾けるぅ！」"
  },
  {
    "name": "藤子",
    "message": "「はあっ！　あっ！　あんっ！　い、いくっ！　いくわっ！」"
  },
  {
    "name": "藤子",
    "message": "「いくっ！　いくいくっ！　いっちゃうっ！　いくぅうん！　いくぅうぅんっ！！」"
  },
  {
    "name": "藤子",
    "message": "「いっくぅうううううううううううううううううううううう！！！」"
  },
  {
    "name": "藤子",
    "message": "「はっ、はあっ！　はあぁっ！　はふっ、はあっ！　……んふうぅ……」"
  },
  {
    "message": "力強く長く……尚人は絶頂の多幸感に浸り呆けた母の膣奥へ熱い精液を注いでいく。"
  },
  {
    "message": "自分の母がこうして種付けされる様子を間近で見た結果……"
  },
  {
    "message": "私は先ほど自分も尚人に中出しされた事を思い出し、女性器が疼き愛液が分泌していくのを感じていた。"
  },
  {
    "name": "尚人",
    "message": "「撫子、フェラで綺麗にしてくれ」"
  },
  {
    "name": "撫子",
    "message": "「ん、わかった」"
  },
  {
    "message": "私は横たえていた身体を起こすと、セックスを終えたばかりの尚人のペニスに顔を近づけていく……"
  },
  {
    "message": "目の前には雄々しくそそり立つ尚人のペニス……その逞しい刀身には、当然のようにお母さんの膣の匂いがたっぷりとこびりついている。"
  },
  {
    "name": "撫子",
    "message": "「……スン……スンスン……」"
  },
  {
    "name": "撫子",
    "message": "（……いやらしい匂い……凄い……むわってくる……）"
  },
  {
    "message": "本来なら顔を背けるような匂いを前に……私は構わず口を開き、尚人の濡れた肉棒をヌルリと口に咥え込ませた。"
  },
  {
    "name": "撫子",
    "message": "「はむっ、ちゅ、ちゅぱっ……んちゅうぅ……」"
  },
  {
    "message": "舌は使わず、まずは窄めた口内の壁だけでペニスを包み、全体に自分の唾液をまぶしていく。"
  },
  {
    "message": "そうして自らの唾液でこびり付いた二人の淫液を薄めさせると、私はペニスを咥えたまま舌で丁寧に肉棒の竿を舐めまわした。"
  },
  {
    "name": "撫子",
    "message": "「れろっ、ちゅっ、ちゅぱっ……れろれろっ……はむっ、ちゅっ、ちゅぱっ……」"
  },
  {
    "message": "フェラチオをするのは嫌いじゃない……どちらかというと好きだったりする。"
  },
  {
    "message": "そもそも、初めからこの味が苦手ではなかった。"
  },
  {
    "message": "……それに排泄器官を口で愛撫するという倒錯的行為は、いやらしい事をしているという感覚を強く刺激して、女性器を熱くさせてくれる。"
  },
  {
    "message": "こうして熱くやわらかい亀頭を口内の壁で擦るだけで……少しだが、自分も気持ちよくなれるのだ。"
  },
  {
    "name": "撫子",
    "message": "「ちゅぱっ、ちゅっ、ちゅるぅ……れろれろっ……ちゅっ、ちゅぱっ、んちゅぅ……」"
  },
  {
    "message": "あとは尚人から上手いと褒められた結果、奉仕の喜びというやつを覚えたのも……私がフェラを好きになった要因の一つだろう。"
  },
  {
    "name": "撫子",
    "message": "（……先走りちょっと出てきた……んっ……美味しい……）"
  },
  {
    "name": "撫子",
    "message": "「はむっ、ちゅっ、ちゅぱっ……ちゅっ、ちゅるっ……んちゅぅ……」"
  },
  {
    "message": "今ではどうすれば尚人が喜ぶのかも熟知しているし、女の子の仕込みをする時にフェラの指導を任される事だってある。"
  },
  {
    "message": "熱心にペニスを丁寧にしゃぶり続けていると、尚人が私を労うように優しく頭を撫でてくれた。"
  },
  {
    "name": "撫子",
    "message": "「……んくっ……んふうぅ……」"
  },
  {
    "message": "それだけで私はとても嬉しくなり……女性器全体がキュンと熱く疼いてしまう。"
  },
  {
    "name": "撫子",
    "message": "（……フェラは好きなんだけど……華穂さまと仲良くする人間として、こういう変態チックな感覚は……直さないとマズいよね……）"
  },
  {
    "message": "そんな事を頭に思い浮かべながら……"
  },
  {
    "message": "……私はこびりついた愛液の味がなくなった後も……"
  },
  {
    "message": "……尚人のペニスを、丹念に舐め続けたのだった……"
  }
]