[
  {
    "message": "藤子の口で肉棒を綺麗にしてもらった後……"
  },
  {
    "message": "俺はいつものように行為後にイチャつきたいという欲求を堪え、洗い場で一人余韻と汗をサッとシャワーで洗い落としていく。"
  },
  {
    "message": "そして同じように汗を流していた藤子と共に再び湯船に戻ると……俺達は示し合わせたかのように、行為前と同じ場所に腰を下ろしたのだった。"
  },
  {
    "name": "藤子",
    "message": "「……ふぅ……」"
  },
  {
    "name": "重明",
    "message": "「お疲れ様です……藤子さん」"
  },
  {
    "name": "藤子",
    "message": "「ふふ……何だかそう言うのは少し違う気がするけど……お疲れ様、重明くん」"
  },
  {
    "message": "笑顔で性行為での労をねぎらい合う仲となった俺と藤子……現時点で、かなり打ち解けていると思ってもいいだろう。"
  },
  {
    "message": "今のこの空気なら言える……俺はそう確信し、ここに来た本題を藤子に投げかける事にした。"
  },
  {
    "name": "重明",
    "message": "「藤子さん、早速ですけど……いいでしょうか？」"
  },
  {
    "name": "藤子",
    "message": "「……撫子の事よね？」"
  },
  {
    "name": "重明",
    "message": "（……うん？）"
  },
  {
    "message": "俺の問いかけに対し、短く切り返した藤子の返答……"
  },
  {
    "message": "その何気ない一言に、俺は何となく違和感のような物を感じ……頭の中で一人首を傾げさせる。"
  },
  {
    "name": "重明",
    "message": "（……取り立てて変な事は言ってないハズなんだけど……今の藤子さんのニュアンス……妙に気になるな……何でだろ……）"
  },
  {
    "name": "重明",
    "message": "「……そうです……撫子ちゃんの話、出来るだけ教えてもらえないでしょうか？」"
  },
  {
    "name": "藤子",
    "message": "「…………」"
  },
  {
    "message": "話題を振ると早々に、藤子はその美しい面持ちを憂いある表情へと変化させる。"
  },
  {
    "message": "……その理由はまるでわからないが、やはり藤子としては、撫子の事件の事を心底語りたくないらしい……"
  },
  {
    "name": "重明",
    "message": "（……けど約束は約束……俺に華穂の気持ちを裏切るような真似をさせておいて、流石に自分はダンマリってのはナシですよ？　藤子さん……）"
  },
  {
    "name": "藤子",
    "message": "「……鍵……」"
  },
  {
    "name": "重明",
    "message": "「……はい？」"
  },
  {
    "name": "藤子",
    "message": "「確か重明くん、あの子の部屋に鍵がかかっていて入れなかったから開けて欲しい……そんな事を言っていましたよね？」"
  },
  {
    "name": "重明",
    "message": "「はい、確かに言いました」"
  },
  {
    "name": "藤子",
    "message": "「なら私がお風呂から上がったら、直ぐに鍵を開けるわ……部屋を自由に調べていいから、私には何も聞かないで欲しい……この条件でどうかしら？」"
  },
  {
    "name": "重明",
    "message": "（……ふむ……）"
  },
  {
    "message": "部屋を調べてもいいが、話は聞かないで欲しい……"
  },
  {
    "message": "つまり明日に日を改めて、俺なり華穂が話を聞いても……藤子は撫子の事を詳しく語る気はないという意味なのだろう。"
  },
  {
    "message": "こちらの犯したリスクの対価としては、少々見合わない気がしなくもないが……"
  },
  {
    "message": "だからと言って、そうまで喋りたくない事を無理に聞くというのも、あまり気が進まない。"
  },
  {
    "name": "重明",
    "message": "（……華穂だって真相の全てをここで知れるとは思ってないだろうし……オッサンの話と、撫子ちゃんの部屋を調べられれば……納得してくれるか？）"
  },
  {
    "message": "それに更なる情報を得たいというなら……藤子が喋る気がない以上、他の人物から情報を聞き出すしかない。"
  },
  {
    "name": "重明",
    "message": "（そうなると……ここを出て……当時撫子ちゃんと同じ女子寮だった頃の白花荘に住んでいた女生徒を探して話を聞く……とかになるんだろうな……）"
  },
  {
    "message": "何にしろ、現時点でこの白花荘にて俺と華穂が出来る事は、精々撫子が暮らしていた部屋に入るぐらいなのは間違いなさそうだ。"
  },
  {
    "name": "重明",
    "message": "「わかりました、それでお願いします」"
  },
  {
    "name": "藤子",
    "message": "「ありがとう……重明くん」"
  },
  {
    "name": "重明",
    "message": "「いえ、こちらこそ……何も言いたくない感じだったのに、無関係の人間が無遠慮に絡んでしまって……本当にすみませんでした……」"
  },
  {
    "name": "藤子",
    "message": "「いいのよ……別に貴方が悪いわけじゃないわ……あまり気にしないで」"
  },
  {
    "message": "もちろん謝ったのは社交辞令……なぜ藤子が語りたがらないのかを知らない以上、俺が彼女に本当の意味で謝罪をするのは不可能に近いだろう。"
  },
  {
    "message": "その語りたがらない理由を出来れば知りたいのだが……流石にこうも嫌がっている女性から、話を無理やり聞き出すほど、こちらも外道ではない。"
  },
  {
    "message": "それにもしかすると……これから行く撫子の部屋に、藤子が語りたくない理由を知る手がかりがあるかもしれない。"
  },
  {
    "name": "重明",
    "message": "（……よし、行くか！）"
  },
  {
    "message": "俺は藤子に別れを告げると、これまでに得た情報を華穂に伝える為、一人風呂場を後にしたのだった……"
  },
  {
    "message": "・\r\n・\r\n・"
  }
]